simphox/__init__.py
simphox/bpm.py
simphox/fdfd.py
simphox/fdtd.py
simphox/grid.py
simphox/mkl.py
simphox/mode.py
simphox/opt.py
simphox/parse.py
simphox/primitives.py
simphox/sim.py
simphox/transform.py
simphox/typing.py
simphox/utils.py
simphox/viz.py
simphox/circuit/__init__.py
simphox/circuit/component.py
simphox/circuit/coupling.py
simphox/circuit/envelope.py
simphox/circuit/forward.py
simphox/circuit/matrix.py
simphox/circuit/rectangular.py
simphox/circuit/vector.py
simphox-0.0.1a8.dist-info/LICENSE
simphox-0.0.1a8.dist-info/METADATA
simphox-0.0.1a8.dist-info/WHEEL
simphox-0.0.1a8.dist-info/top_level.txt
simphox-0.0.1a8.dist-info/RECORD
