Metadata-Version: 2.1
Name: simphox
Version: 0.0.1a8
Summary: UNKNOWN
Home-page: UNKNOWN
License: UNKNOWN
Platform: UNKNOWN
Requires-Dist: numpy
Requires-Dist: scipy
Requires-Dist: pandas
Requires-Dist: jaxlib
Requires-Dist: jax
Requires-Dist: scikit-image
Requires-Dist: pydantic
Requires-Dist: xarray
Provides-Extra: interactive
Requires-Dist: matplotlib ; extra == 'interactive'
Requires-Dist: jupyterlab ; extra == 'interactive'
Requires-Dist: holoviews ; extra == 'interactive'
Requires-Dist: bokeh ; extra == 'interactive'
